my_sdk/__init__.py
my_sdk/api.c
my_sdk/api.cp313-win_amd64.pyd
my_sdk/api.py
my_sdk/core.c
my_sdk/core.cp313-win_amd64.pyd
my_sdk/core.py
harry_complex_sdk_mamotion-1.0.0.dist-info/METADATA
harry_complex_sdk_mamotion-1.0.0.dist-info/WHEEL
harry_complex_sdk_mamotion-1.0.0.dist-info/top_level.txt
harry_complex_sdk_mamotion-1.0.0.dist-info/RECORD
